{
  "id": "presentation-beamer",
  "name": "Presentation (Beamer)",
  "description": "A modern, clean presentation template using the Beamer class",
  "category": "Presentation",
  "tags": ["beamer", "presentation", "slides"],
  "mainFile": "main.tex",
  "thumbnail": "thumbnail.png",
  "files": {
    "main.tex": "\\documentclass[aspectratio=169]{beamer}\n\\usepackage[utf8]{inputenc}\n\\usepackage[T1]{fontenc}\n\\usepackage{amsmath,amsfonts,amssymb}\n\\usepackage{graphicx}\n\n% Theme and color scheme\n\\usetheme{Madrid}\n\\usecolortheme{blue}\n\n% Remove navigation symbols\n\\setbeamertemplate{navigation symbols}{}\n\n% Title page information\n\\title{Your Presentation Title}\n\\subtitle{A subtitle if needed}\n\\author{Your Name}\n\\institute{Your Institution}\n\\date{\\today}\n\n% Logo (uncomment and provide logo file)\n% \\logo{\\includegraphics[height=1cm]{logo.png}}\n\n\\begin{document}\n\n% Title slide\n\\begin{frame}\n  \\titlepage\n\\end{frame}\n\n% Outline\n\\begin{frame}\n  \\frametitle{Outline}\n  \\tableofcontents\n\\end{frame}\n\n\\section{Introduction}\n\n\\begin{frame}\n  \\frametitle{Introduction}\n  \\begin{itemize}\n    \\item Welcome to your presentation\n    \\item This is a sample slide with bullet points\n    \\item You can customize the content as needed\n  \\end{itemize}\n\\end{frame}\n\n\\begin{frame}\n  \\frametitle{Problem Statement}\n  \\begin{block}{Key Question}\n    What problem are you trying to solve?\n  \\end{block}\n  \n  \\begin{alertblock}{Challenge}\n    What makes this problem challenging?\n  \\end{alertblock}\n  \n  \\begin{exampleblock}{Approach}\n    How do you plan to address it?\n  \\end{exampleblock}\n\\end{frame}\n\n\\section{Methodology}\n\n\\begin{frame}\n  \\frametitle{Our Approach}\n  \\begin{columns}\n    \\begin{column}{0.5\\textwidth}\n      \\begin{itemize}\n        \\item Step 1: Data collection\n        \\item Step 2: Analysis\n        \\item Step 3: Validation\n      \\end{itemize}\n    \\end{column}\n    \\begin{column}{0.5\\textwidth}\n      \\begin{figure}\n        \\centering\n        % \\includegraphics[width=\\textwidth]{methodology.png}\n        \\caption{Methodology overview}\n      \\end{figure}\n    \\end{column}\n  \\end{columns}\n\\end{frame}\n\n\\section{Results}\n\n\\begin{frame}\n  \\frametitle{Key Results}\n  \\begin{itemize}\n    \\item<1-> First important result\n    \\item<2-> Second important result\n    \\item<3-> Third important result\n  \\end{itemize}\n  \n  \\onslide<4->{\n    \\begin{block}{Summary}\n      All results point to the same conclusion.\n    \\end{block}\n  }\n\\end{frame}\n\n\\begin{frame}\n  \\frametitle{Data Visualization}\n  \\begin{figure}\n    \\centering\n    % \\includegraphics[width=0.8\\textwidth]{results-chart.png}\n    \\caption{Results visualization}\n  \\end{figure}\n\\end{frame}\n\n\\section{Conclusion}\n\n\\begin{frame}\n  \\frametitle{Conclusions}\n  \\begin{itemize}\n    \\item We successfully addressed the problem\n    \\item Our approach shows promising results\n    \\item Future work includes...\n  \\end{itemize}\n\\end{frame}\n\n\\begin{frame}\n  \\frametitle{Questions?}\n  \\begin{center}\n    {\\Huge Thank you!}\n    \n    \\vspace{1cm}\n    \n    {\\large Questions and Discussion}\n    \n    \\vspace{1cm}\n    \n    Contact: your.email@institution.edu\n  \\end{center}\n\\end{frame}\n\n\\end{document}"
  }
}
